boost_game/__init__.py
boost_game/__main__.py
boost_game/boost.py
boost_game/bot.py
boost_game/rulesets.py
boost_game/graphics/__init__.py
boost_game/graphics/board_svg.py
boost_game/graphics/svg_to_png.py
boost_game/graphics/pieces/dragon.svg
boost_game/graphics/pieces/black/knight.svg
boost_game/graphics/pieces/black/pawn.svg
boost_game/graphics/pieces/black/tower.svg
boost_game/graphics/pieces/blue/knight.svg
boost_game/graphics/pieces/blue/pawn.svg
boost_game/graphics/pieces/blue/tower.svg
boost_game/graphics/pieces/cyan/knight.svg
boost_game/graphics/pieces/cyan/pawn.svg
boost_game/graphics/pieces/cyan/tower.svg
boost_game/graphics/pieces/green/knight.svg
boost_game/graphics/pieces/green/pawn.svg
boost_game/graphics/pieces/green/tower.svg
boost_game/graphics/pieces/magenta/knight.svg
boost_game/graphics/pieces/magenta/pawn.svg
boost_game/graphics/pieces/magenta/tower.svg
boost_game/graphics/pieces/orange/knight.svg
boost_game/graphics/pieces/orange/pawn.svg
boost_game/graphics/pieces/orange/tower.svg
boost_game/graphics/pieces/pink/knight.svg
boost_game/graphics/pieces/pink/pawn.svg
boost_game/graphics/pieces/pink/tower.svg
boost_game/graphics/pieces/red/knight.svg
boost_game/graphics/pieces/red/pawn.svg
boost_game/graphics/pieces/red/tower.svg
boost_game/graphics/pieces/violet/knight.svg
boost_game/graphics/pieces/violet/pawn.svg
boost_game/graphics/pieces/violet/tower.svg
boost_game/graphics/pieces/white/knight.svg
boost_game/graphics/pieces/white/pawn.svg
boost_game/graphics/pieces/white/tower.svg
boost_game/graphics/pieces/yellow/knight.svg
boost_game/graphics/pieces/yellow/pawn.svg
boost_game/graphics/pieces/yellow/tower.svg
boost_game-1.2.0.dist-info/entry_points.txt
boost_game-1.2.0.dist-info/LICENSE.txt
boost_game-1.2.0.dist-info/WHEEL
boost_game-1.2.0.dist-info/METADATA
boost_game-1.2.0.dist-info/RECORD
