Metadata-Version: 2.1
Name: boost-game
Version: 1.2.0
Summary: Python implementation of the Boost board game, for CLI and Discord
Author-email: Aaron Friesen <maugrift@maugrift.com>
Classifier: License :: OSI Approved :: GNU Affero General Public License v3 or later (AGPLv3+)
Requires-Dist: discord.py ~=1.7.3
Requires-Dist: termcolor ~=1.1.0
Project-URL: Home, https://github.com/Maugrift/boost
